morse/__init__.py
morse/auxil.py
morse/echellediagram.py
morse/eigenvalue.py
morse/idmap.py
morse/pattern.py
morse/spectrum.py
morse/lambda/lambda_m-0.txt
morse/lambda/lambda_m-1.txt
morse/lambda/lambda_m-2.txt
morse/lambda/lambda_m-3.txt
morse/lambda/lambda_m-4.txt
morse/lambda/lambda_m-5.txt
morse/lambda/lambda_m0.txt
morse/lambda/lambda_m1.txt
morse/lambda/lambda_m1_k-1.txt
morse/lambda/lambda_m1_k-2.txt
morse/lambda/lambda_m1_k-3.txt
morse/lambda/lambda_m2.txt
morse/lambda/lambda_m3.txt
morse/lambda/lambda_m4.txt
morse/lambda/lambda_m5.txt
morse_asteroseismo-0.0.3.dist-info/LICENSE
morse_asteroseismo-0.0.3.dist-info/METADATA
morse_asteroseismo-0.0.3.dist-info/WHEEL
morse_asteroseismo-0.0.3.dist-info/top_level.txt
morse_asteroseismo-0.0.3.dist-info/RECORD
