Metadata-Version: 2.1
Name: morse-asteroseismo
Version: 0.0.3
Summary: Asteroseismic analysis of gamma Dor and SPB stars
Home-page: https://github.com/schristophe/morse
Author: Steven Christophe
Author-email: steven.christophe@obspm.fr
License: UNKNOWN
Project-URL: Documentation, https://morse-asteroseismo.readthedocs.io/
Platform: UNKNOWN
Classifier: Programming Language :: Python :: 3
Classifier: License :: OSI Approved :: GNU General Public License v3 (GPLv3)
Classifier: Operating System :: OS Independent
Classifier: Topic :: Scientific/Engineering :: Astronomy
Classifier: Intended Audience :: Science/Research
Classifier: Development Status :: 3 - Alpha
Requires-Python: >=3.6
